chess/__init__.py
chess/board.py
chess/piece.py
chess/app/__init__.py
chess/app/__main__.py
chess/app/controller/__init__.py
chess/app/controller/game_controller.py
chess/app/view/__init__.py
chess/app/view/board_view.py
chess_cli_bshio-0.0.1.dist-info/LICENSE
chess_cli_bshio-0.0.1.dist-info/METADATA
chess_cli_bshio-0.0.1.dist-info/WHEEL
chess_cli_bshio-0.0.1.dist-info/entry_points.txt
chess_cli_bshio-0.0.1.dist-info/top_level.txt
chess_cli_bshio-0.0.1.dist-info/RECORD
