Metadata-Version: 2.1
Name: chess-cli-bshio
Version: 0.0.1
Summary: Cli game of chess
Home-page: https://github.com/shimanekb/chess
Author: Brandon Shimanek
Author-email: brandon.j.shimanek@gmail.com
License: UNKNOWN
Platform: UNKNOWN
Classifier: Programming Language :: Python :: 3
Classifier: License :: OSI Approved :: Apache Software License
Classifier: Operating System :: OS Independent
